{
  "generatedAt": "2026-05-01T16:48:33.535Z",
  "sources": [
    {
      "name": "YouTube channel feeds",
      "url": "https://www.youtube.com/feeds/videos.xml"
    },
    {
      "name": "Curated Twitch channels",
      "url": "https://www.twitch.tv/directory"
    }
  ],
  "series": [
    {
      "id": "f1",
      "name": "Formula 1"
    },
    {
      "id": "f2",
      "name": "Formula 2"
    },
    {
      "id": "f3",
      "name": "Formula 3"
    },
    {
      "id": "motogp",
      "name": "MotoGP"
    },
    {
      "id": "wec",
      "name": "WEC"
    },
    {
      "id": "indycar",
      "name": "IndyCar"
    },
    {
      "id": "rally",
      "name": "Rally"
    },
    {
      "id": "other",
      "name": "Other"
    }
  ],
  "broadcasts": [
    {
      "platform": "youtube",
      "platformLabel": "YouTube",
      "statusLabel": "Live now",
      "title": "Drift Masters Round 1 - Italy - Top16",
      "channel": "Red Bull Motorsports",
      "videoId": "s1QDFB_anHM",
      "url": "https://www.youtube.com/watch?v=s1QDFB_anHM",
      "series": [
        "other"
      ],
      "seriesLabels": [
        "Other"
      ]
    },
    {
      "platform": "youtube",
      "platformLabel": "YouTube",
      "statusLabel": "Live now",
      "title": "Drift Masters Round 1 - Italy - Top32",
      "channel": "Red Bull Motorsports",
      "videoId": "lDf3FqIN0ic",
      "url": "https://www.youtube.com/watch?v=lDf3FqIN0ic",
      "series": [
        "other"
      ],
      "seriesLabels": [
        "Other"
      ]
    },
    {
      "platform": "twitch",
      "platformLabel": "Twitch",
      "statusLabel": "Live channel",
      "title": "iRacing official live hub",
      "channel": "iracing",
      "url": "https://www.twitch.tv/iracing",
      "series": [
        "other"
      ],
      "seriesLabels": [
        "Other"
      ],
      "embedNote": "Twitch embeds depend on the current site hostname. If embedding is unavailable, open the channel directly."
    },
    {
      "platform": "twitch",
      "platformLabel": "Twitch",
      "statusLabel": "Live channel",
      "title": "RaceSpot broadcast channel",
      "channel": "racespot",
      "url": "https://www.twitch.tv/racespot",
      "series": [
        "other"
      ],
      "seriesLabels": [
        "Other"
      ],
      "embedNote": "Twitch embeds depend on the current site hostname. If embedding is unavailable, open the channel directly."
    }
  ]
}
